ffmpeg8_binaries/__init__.py
ffmpeg8_binaries/binaries/linux/x86_64/ffmpeg
ffmpeg8_binaries-0.3.dist-info/METADATA
ffmpeg8_binaries-0.3.dist-info/WHEEL
ffmpeg8_binaries-0.3.dist-info/top_level.txt
ffmpeg8_binaries-0.3.dist-info/RECORD
